setup.py
src/flymph/__init__.py
src/flymph/flymph.py
src/flymph.egg-info/PKG-INFO
src/flymph.egg-info/SOURCES.txt
src/flymph.egg-info/dependency_links.txt
src/flymph.egg-info/entry_points.txt
src/flymph.egg-info/not-zip-safe
src/flymph.egg-info/requires.txt
src/flymph.egg-info/top_level.txt