Metadata-Version: 1.0
Name: flymph
Version: 0.1.3
Summary: Flask as Lymph Web API
Home-page: https://github.com/eightnoteight/flymph
Author: Srinivas Devaki
Author-email: mr.eightnoteight@gmail.com
License: MIT License
Keywords: flask lymph web-api
Platform: UNKNOWN
